osom_work/__init__.py
osom_work/__main__.py
osom_work/arguments.py
osom_work/entrypoint.py
osom_work/apps/__init__.py
osom_work/apps/master/__init__.py
osom_work/apps/worker/__init__.py
osom_work/assets/__init__.py
osom_work/logging/__init__.py
osom_work/logging/colored_formatter.py
osom_work/logging/logging.py
osom_work/www/__init__.py
osom_work-0.0.4.dist-info/LICENSE
osom_work-0.0.4.dist-info/METADATA
osom_work-0.0.4.dist-info/WHEEL
osom_work-0.0.4.dist-info/entry_points.txt
osom_work-0.0.4.dist-info/top_level.txt
osom_work-0.0.4.dist-info/RECORD
